django_before-1.0.0.dist-info/WHEEL
django_before-1.0.0.dist-info/metadata.json
django_before-1.0.0.dist-info/RECORD
django_before-1.0.0.dist-info/top_level.txt
django_before-1.0.0.dist-info/DESCRIPTION.rst
django_before-1.0.0.dist-info/METADATA
django_before/settings_path.py
django_before/__init__.py
django_before/json_settings.py
django_before/exceptions.py
