Metadata-Version: 2.0
Name: django-before
Version: 1.0.0
Summary: Tools that are needed BEFORE any others in each django project
Home-page: https://github.com/alekseyr/django-before
Author: Aleksey Rezvov
Author-email: aleksey.rezvov@gmail.com
License: MIT
Keywords: django settings.py
Platform: UNKNOWN
Classifier: Development Status :: 3 - Alpha
Classifier: Intended Audience :: Developers
Classifier: License :: OSI Approved :: MIT License
Classifier: Programming Language :: Python :: 3
